{"simulations":[{"name":"testEVENT","states":[{"name":"ola","maxCapacity":7,"stateID":36},{"name":"adeus","maxCapacity":10,"stateID":37}],"transitions":[{"source":null,"target":{"name":"ola","maxCapacity":7,"stateID":36},"hl7Event":"ADT_A01 - Admit/visit Notification","simulationName":"testEVENT","probability":0.8,"frequency":1},{"source":{"name":"adeus","maxCapacity":10,"stateID":37},"target":null,"hl7Event":null,"simulationName":"testEVENT","probability":1.0,"frequency":5},{"source":{"name":"ola","maxCapacity":7,"stateID":36},"target":{"name":"adeus","maxCapacity":10,"stateID":37},"hl7Event":"MSH|^~\\&|TestSendingApplication|TestSendingFacility|TestReceivingApplication|TestReceivingFacility|20230526120000||ADT^A03^ADT_A03|1201|P|2.5.1\rEVN||20230526120000\rPID|||623529||Martins^Pedro||19590722|F\r","simulationName":"testEVENT","probability":0.8,"frequency":3},{"source":{"name":"ola","maxCapacity":7,"stateID":36},"target":{"name":"adeus","maxCapacity":10,"stateID":37},"hl7Event":"MSH|^~\\&|TestSendingApplication|TestSendingFacility|TestReceivingApplication|TestReceivingFacility|20230526120000||ADT^A03^ADT_A03|1201|P|2.5.1\rEVN||20230526120000\rPID|||623529||Martins^Pedro||19590722|F\r","simulationName":"testEVENT","probability":0.8,"frequency":3}],"events":["ADT_A01 - Admit/visit Notification","ADT_A02 - Transfer a Patient","ADT_A03 - Discharge/End Visit","ORM_O01 - General Order ","ORU_R01 - Unsolicited transmission of an observation message"],"startState":{"name":"ola","maxCapacity":7,"stateID":36},"endState":{"name":"adeus","maxCapacity":10,"stateID":37}}]}